delphy/__init__.py
delphy-0.0.0.dist-info/METADATA
delphy-0.0.0.dist-info/WHEEL
delphy-0.0.0.dist-info/RECORD
