Metadata-Version: 2.1
Name: delphy
Version: 0.0.0
Summary: DEep Learning for PHYlodynamics
Author: Gabriele Marino
Author-email: gabmarino.8601@gmail.com
Requires-Python: >=3.10,<4.0
Classifier: Programming Language :: Python :: 3
Classifier: Programming Language :: Python :: 3.10
Classifier: Programming Language :: Python :: 3.11
Classifier: Programming Language :: Python :: 3.12
